Workbook

Sheet Cleaned_Data
A1: job_title | B1: company | C1: city | D1: sector | E1: employment_type | F1: experience_required | G1: salary_pkr_month | H1: platform | I1: date_posted_or_seen | J1: source_url | K1: notes | L1: city_clean | M1: work_mode | N1: contract_type | O1: experience_level | P1: salary_disclosed | Q1: date_parsed | R1: salary_currency | S1: salary_value_monthly | T1: salary_note | U1: search_text
A2: Data Analyst | B2: Millat Tractors | C2: Rawalpindi | D2: Manufacturing | E2: Hybrid | F2: Senior (5-8 yrs) | G2: Not disclosed | H2: Rozee.pk | I2: 2026-06 | J2: https://www.rozee.pk/search/data-analyst-jobs-in-pakistan | K2: From Rozee.pk live search results | L2: Rawalpindi | M2: Hybrid | N2: Not disclosed | O2: Senior | P2: No | Q2: 2026-06-01 | U2: data analyst | from rozee.pk live search results | manufacturing
A3: Upwork Bidder / Business Analyst | B3: Dotgenic Systems | C3: Lahore | D3: IT Services | E3: Not disclosed | F3: Fresh | G3: Not disclosed | H3: Rozee.pk | I3: 2026-06-10 | J3: https://www.rozee.pk/search/data-analyst-jobs-in-pakistan | K3: Client acquisition + data analysis role | L3: Lahore | M3: Not disclosed | N3: Not disclosed | O3: Entry/Fresh | P3: No | Q3: 2026-06-10 | U3: upwork bidder / business analyst | client acquisition + data analysis role | it services
A4: Associate Financial Analyst | B4: ASTO Life Sciences | C4: Lahore | D4: Pharma/Life Sciences | E4: Not disclosed | F4: 3 years | G4: 120000-120000 | H4: Rozee.pk | I4: 2026-06-15 | J4: https://www.rozee.pk/search/data-analyst-jobs-in-pakistan | K4: Only listing with exact disclosed salary | L4: Lahore | M4: Not disclosed | N4: Not disclosed | O4: Mid | P4: Yes | Q4: 2026-06-15 | R4: PKR | S4: 120000 | U4: associate financial analyst | only listing with exact disclosed salary | pharma/life sciences
A5: Financial Analyst | B5: KSB Pumps Company Limited | C5: Lahore | D5: Manufacturing | E5: Not disclosed | F5: Experienced | G5: Not disclosed | H5: Rozee.pk | I5: 2026-06 | J5: https://www.rozee.pk/search/data-analyst-jobs-in-pakistan | L5: Lahore | M5: Not disclosed | N5: Not disclosed | O5: Mid | P5: No | Q5: 2026-06-01 | U5: financial analyst | | manufacturing
A6: Senior Project Analyst | B6: Now IT Solutions | C6: Not disclosed | D6: IT Services | E6: Not disclosed | F6: Experienced | G6: Not disclosed | H6: Rozee.pk | I6: 2026-06 | J6: https://www.rozee.pk/search/data-analyst-jobs-in-pakistan | K6: Techno-functional PMO role | L6: Not disclosed | M6: Not disclosed | N6: Not disclosed | O6: Mid | P6: No | Q6: 2026-06-01 | U6: senior project analyst | techno-functional pmo role | it services
A7: Senior Analyst | B7: Bank Al Habib Limited | C7: Not disclosed | D7: Banking | E7: Not disclosed | F7: 3+ years | G7: Not disclosed | H7: Rozee.pk | I7: 2026-06 | J7: https://www.rozee.pk/search/data-analyst-jobs-in-pakistan | K7: Power BI / Power Query skills required | L7: Not disclosed | M7: Not disclosed | N7: Not disclosed | O7: Mid | P7: No | Q7: 2026-06-01 | U7: senior analyst | power bi / power query skills required | banking
A8: Data and Reporting Analyst | B8: Confidential (NGO/Program) | C8: Not disclosed | D8: NGO & Development | E8: Not disclosed | F8: Not disclosed | G8: Not disclosed | H8: Rozee.pk | I8: 2026-06 | J8: https://www.rozee.pk/search/data-analyst-jobs-in-pakistan | K8: Program data accuracy and integrity role | L8: Not disclosed | M8: Not disclosed | N8: Not disclosed | O8: Not disclosed | P8: No | Q8: 2026-06-01 | U8: data and reporting analyst | program data accuracy and integrity role | ngo & development
A9: MIS Analyst | B9: Confidential (Health Program) | C9: Not disclosed | D9: NGO & Development | E9: Not disclosed | F9: Not disclosed | G9: Not disclosed | H9: Rozee.pk | I9: 2026-06 | J9: https://www.rozee.pk/search/data-analyst-jobs-in-pakistan | K9: Health Management Information Systems | L9: Not disclosed | M9: Not disclosed | N9: Not disclosed | O9: Not disclosed | P9: No | Q9: 2026-06-01 | U9: mis analyst | health management information systems | ngo & development
A10: Junior SAP Analytics Cloud Analyst | B10: Confidential Multinational | C10: Not disclosed | D10: FMCG/Multinational | E10: Entry Level | F10: Entry level | G10: Not disclosed | H10: Rozee.pk | I10: 2026-06 | J10: https://www.rozee.pk/search/data-analyst-jobs-in-pakistan | K10: SAP Analytics Cloud dashboarding | L10: Not disclosed | M10: Not disclosed | N10: Not disclosed | O10: Entry/Fresh | P10: No | Q10: 2026-06-01 | U10: junior sap analytics cloud analyst | sap analytics cloud dashboarding | fmcg/multinational
A11: Data Analyst Associate | B11: Gazala Group | C11: Karachi (North Nazimabad) | D11: Healthcare Consultancy | E11: Not disclosed | F11: Not disclosed | G11: Not disclosed | H11: Rozee.pk | I11: 2026-06 | J11: https://www.rozee.pk/search/data-analyst-jobs-in-pakistan | K11: Excel PivotTables, R, data visualization | L11: Karachi | M11: Not disclosed | N11: Not disclosed | O11: Not disclosed | P11: No | Q11: 2026-06-01 | U11: data analyst associate | excel pivottables, r, data visualization | healthcare consultancy
A12: Data Research and Data Analyst | B12: S&N Consulting Group Pvt Ltd | C12: Multan (Shah Rukn-e-Alam) | D12: Consulting | E12: Not disclosed | F12: Not disclosed | G12: Not disclosed | H12: Rozee.pk | I12: 2026-06 | J12: https://www.rozee.pk/search/data-analyst-jobs-in-pakistan | K12: Data mining and database management | L12: Multan | M12: Not disclosed | N12: Not disclosed | O12: Not disclosed | P12: No | Q12: 2026-06-01 | U12: data research and data analyst | data mining and database management | consulting
A13: Data Analyst | B13: Rozee (internal posting) | C13: Karachi | D13: Agri-Tech | E13: Not disclosed | F13: Not disclosed | G13: Not disclosed | H13: Rozee.pk | I13: 2026-06 | J13: https://www.rozee.pk/EN/rozee-data-analyst-jobs-1555112 | K13: Crop price prediction using Python and Power BI | L13: Karachi | M13: Not disclosed | N13: Not disclosed | O13: Not disclosed | P13: No | Q13: 2026-06-01 | U13: data analyst | crop price prediction using python and power bi | agri-tech
A14: Data Analyst/Reporting - Microsoft Power BI | B14: GRID Systems | C14: Islamabad | D14: IT Services | E14: Not disclosed | F14: Not disclosed | G14: Not disclosed | H14: Glassdoor | I14: 2026-06 | J14: https://www.glassdoor.com/Job/pakistan-data-analyst-jobs-SRCH_IL.0,8_IN192_KO9,21.htm | K14: Company rating 4.6/5 on Glassdoor | L14: Islamabad | M14: Not disclosed | N14: Not disclosed | O14: Not disclosed | P14: No | Q14: 2026-06-01 | U14: data analyst/reporting - microsoft power bi | company rating 4.6/5 on glassdoor | it services
A15: Data Conversion Analyst | B15: Contour Software | C15: Lahore | D15: IT Services | E15: Not disclosed | F15: Not disclosed | G15: Not disclosed | H15: Glassdoor | I15: 2026-06 | J15: https://www.glassdoor.com/Job/pakistan-data-analyst-jobs-SRCH_IL.0,8_IN192_KO9,21.htm | K15: Company rating 4.4/5 on Glassdoor | L15: Lahore | M15: Not disclosed | N15: Not disclosed | O15: Not disclosed | P15: No | Q15: 2026-06-01 | U15: data conversion analyst | company rating 4.4/5 on glassdoor | it services
A16: Data Analyst | B16: Metallicus | C16: Pakistan (Remote/Hybrid) | D16: Fintech/Blockchain | E16: Not disclosed | F16: Not disclosed | G16: Not disclosed | H16: Glassdoor | I16: 2026-06 | J16: https://www.glassdoor.com/Job/pakistan-data-analyst-jobs-SRCH_IL.0,8_IN192_KO9,21.htm | K16: Company rating 4.0/5 on Glassdoor | L16: Remote/Unspecified | M16: Not disclosed | N16: Not disclosed | O16: Not disclosed | P16: No | Q16: 2026-06-01 | U16: data analyst | company rating 4.0/5 on glassdoor | fintech/blockchain
A17: Data Analyst | B17: Dignosco | C17: Lahore | D17: EdTech/Consulting | E17: Full-time | F17: Not disclosed | G17: 30000-35000 | H17: Glassdoor | I17: 2026-06 | J17: https://www.glassdoor.com/Job/lahore-data-analyst-jobs-SRCH_IL.0,6_IC3206630_KO7,19.htm | K17: Job Code 0019/14; Department Counselling; exact disclosed salary range | L17: Lahore | M17: Not disclosed | N17: Full-time | O17: Not disclosed | P17: Yes | Q17: 2026-06-01 | R17: PKR | S17: 32500 | U17: data analyst | job code 0019/14; department counselling; exact disclosed salary range | edtech/consulting
A18: Lead/Senior Data Analyst - Python/SQL | B18: ValueMomentum | C18: Pakistan | D18: IT Services / Insurance Tech | E18: Not disclosed | F18: Not disclosed | G18: Not disclosed | H18: Glassdoor | I18: 2026-05 | J18: https://www.glassdoor.com/Job/pakistan-data-analytics-jobs-SRCH_IL.0,8_IN192_KO9,23.htm | K18: UK/US P&C Insurance domain experience required | L18: Remote/Unspecified | M18: Not disclosed | N18: Not disclosed | O18: Not disclosed | P18: No | Q18: 2026-05-01 | U18: lead/senior data analyst - python/sql | uk/us p&c insurance domain experience required | it services / insurance tech
A19: Data Analyst | B19: Creative Chaos | C19: Not disclosed | D19: IT Services | E19: Not disclosed | F19: Not disclosed | G19: Not disclosed | H19: Bayt.com | I19: 2026-05 | J19: https://www.bayt.com/en/pakistan/jobs/data-analyst-jobs/ | L19: Not disclosed | M19: Not disclosed | N19: Not disclosed | O19: Not disclosed | P19: No | Q19: 2026-05-01 | U19: data analyst | | it services
A20: Sr. Data Scientist | B20: Confidential | C20: Karachi/Lahore/Islamabad | D20: IT Services | E20: Onsite | F20: Senior | G20: PKR salary (not disclosed) | H20: Bayt.com | I20: 2026-05 | J20: https://www.bayt.com/en/pakistan/jobs/data-analyst-jobs/ | L20: Multi-city | M20: Onsite | N20: Not disclosed | O20: Senior | P20: No | Q20: 2026-05-01 | U20: sr. data scientist | | it services
A21: Senior Manager Data Modeler | B21: MetLife (MGCC) | C21: Karachi/Islamabad | D21: Insurance/Global Capability Center | E21: Onsite | F21: Senior/Manager | G21: Not disclosed | H21: Bayt.com | I21: 2026-05 | J21: https://www.bayt.com/en/pakistan/jobs/data-analyst-jobs/ | K21: Morning shift; global capability center role | L21: Multi-city | M21: Onsite | N21: Not disclosed | O21: Senior | P21: No | Q21: 2026-05-01 | U21: senior manager data modeler | morning shift; global capability center role | insurance/global capability center
A22: Data Engineer | B22: Confidential | C22: Karachi | D22: Technology | E22: Not disclosed | F22: Not disclosed | G22: Not disclosed | H22: LinkedIn | I22: 2026-06 | J22: https://pk.linkedin.com/jobs/data-analyst-jobs | K22: Actively hiring | L22: Karachi | M22: Not disclosed | N22: Not disclosed | O22: Not disclosed | P22: No | Q22: 2026-06-01 | U22: data engineer | actively hiring | technology
A23: Power BI Expert | B23: Confidential | C23: Rawalpindi | D23: Technology | E23: Not disclosed | F23: Not disclosed | G23: Not disclosed | H23: LinkedIn | I23: 2026-06 | J23: https://pk.linkedin.com/jobs/data-analyst-jobs | L23: Rawalpindi | M23: Not disclosed | N23: Not disclosed | O23: Not disclosed | P23: No | Q23: 2026-06-01 | U23: power bi expert | | technology
A24: Business Intelligence Specialist | B24: Confidential | C24: Lahore | D24: Technology | E24: Not disclosed | F24: Not disclosed | G24: Not disclosed | H24: LinkedIn | I24: 2026-06 | J24: https://pk.linkedin.com/jobs/data-analyst-jobs | K24: Actively hiring | L24: Lahore | M24: Not disclosed | N24: Not disclosed | O24: Not disclosed | P24: No | Q24: 2026-06-01 | U24: business intelligence specialist | actively hiring | technology
A25: Senior Data Analyst | B25: Confidential | C25: Punjab | D25: Technology | E25: Not disclosed | F25: Senior | G25: Not disclosed | H25: LinkedIn | I25: 2026-06 | J25: https://pk.linkedin.com/jobs/data-analyst-jobs | K25: Actively hiring | L25: Punjab (unspecified city) | M25: Not disclosed | N25: Not disclosed | O25: Senior | P25: No | Q25: 2026-06-01 | U25: senior data analyst | actively hiring | technology
A26: Remote Data Science Analyst | B26: Confidential | C26: Pakistan (Remote) | D26: Technology | E26: Remote | F26: Not disclosed | G26: Not disclosed | H26: LinkedIn | I26: 2026-06 | J26: https://pk.linkedin.com/jobs/data-analyst-jobs | K26: Actively hiring | L26: Remote/Unspecified | M26: Remote | N26: Not disclosed | O26: Not disclosed | P26: No | Q26: 2026-06-01 | U26: remote data science analyst | actively hiring | technology
A27: Analyst - Insights & Analytics | B27: Confidential | C27: Islamabad | D27: Technology | E27: Not disclosed | F27: Not disclosed | G27: Not disclosed | H27: LinkedIn | I27: 2026-06 | J27: https://pk.linkedin.com/jobs/data-analyst-jobs | K27: Actively hiring | L27: Islamabad | M27: Not disclosed | N27: Not disclosed | O27: Not disclosed | P27: No | Q27: 2026-06-01 | U27: analyst - insights & analytics | actively hiring | technology
A28: Data Analyst - Residual Value Monetisation | B28: Confidential | C28: Lahore | D28: Automotive/Fintech | E28: Onsite | F28: Not disclosed | G28: USD salary (not disclosed) | H28: LinkedIn | I28: 2026-06 | J28: https://pk.linkedin.com/jobs/data-analyst-jobs | K28: Rare USD-denominated onsite role | L28: Lahore | M28: Onsite | N28: Not disclosed | O28: Not disclosed | P28: No | Q28: 2026-06-01 | U28: data analyst - residual value monetisation | rare usd-denominated onsite role | automotive/fintech
A29: Python Data Analyst | B29: Confidential | C29: Islamabad | D29: Technology | E29: Not disclosed | F29: Not disclosed | G29: Not disclosed | H29: LinkedIn | I29: 2026-06 | J29: https://pk.linkedin.com/jobs/data-analyst-jobs | K29: Actively hiring | L29: Islamabad | M29: Not disclosed | N29: Not disclosed | O29: Not disclosed | P29: No | Q29: 2026-06-01 | U29: python data analyst | actively hiring | technology
A30: BI Developer | B30: Confidential | C30: Lahore | D30: Technology | E30: Not disclosed | F30: Not disclosed | G30: Not disclosed | H30: LinkedIn | I30: 2026-06 | J30: https://pk.linkedin.com/jobs/data-analyst-jobs | K30: Actively hiring | L30: Lahore | M30: Not disclosed | N30: Not disclosed | O30: Not disclosed | P30: No | Q30: 2026-06-01 | U30: bi developer | actively hiring | technology
A31: Data Analyst - Crystal Reports | B31: Confidential | C31: Karachi | D31: Technology | E31: Not disclosed | F31: Not disclosed | G31: Not disclosed | H31: LinkedIn | I31: 2026-06 | J31: https://pk.linkedin.com/jobs/data-analytics-jobs | L31: Karachi | M31: Not disclosed | N31: Not disclosed | O31: Not disclosed | P31: No | Q31: 2026-06-01 | U31: data analyst - crystal reports | | technology
A32: Assistant Manager - Business Intelligence | B32: Confidential | C32: Islamabad | D32: Technology | E32: Not disclosed | F32: Assistant Manager | G32: Not disclosed | H32: LinkedIn | I32: 2026-06 | J32: https://pk.linkedin.com/jobs/data-analytics-jobs | K32: Actively hiring | L32: Islamabad | M32: Not disclosed | N32: Not disclosed | O32: Senior | P32: No | Q32: 2026-06-01 | U32: assistant manager - business intelligence | actively hiring | technology
A33: Business Intelligence Analyst | B33: Confidential | C33: Lahore (Johar Town) | D33: Technology | E33: Not disclosed | F33: Not disclosed | G33: Not disclosed | H33: LinkedIn | I33: 2026-06 | J33: https://pk.linkedin.com/jobs/data-analytics-jobs | L33: Lahore | M33: Not disclosed | N33: Not disclosed | O33: Not disclosed | P33: No | Q33: 2026-06-01 | U33: business intelligence analyst | | technology
A34: Lead Data Analyst | B34: Confidential | C34: Lahore | D34: Technology | E34: Not disclosed | F34: Lead | G34: Not disclosed | H34: LinkedIn | I34: 2026-06 | J34: https://pk.linkedin.com/jobs/data-analytics-jobs | K34: Actively hiring | L34: Lahore | M34: Not disclosed | N34: Not disclosed | O34: Senior | P34: No | Q34: 2026-06-01 | U34: lead data analyst | actively hiring | technology
A35: Data Analyst (Onsite Lahore) | B35: Confidential | C35: Lahore | D35: Technology | E35: Onsite | F35: Not disclosed | G35: USD salary (not disclosed) | H35: LinkedIn | I35: 2026-06 | J35: https://pk.linkedin.com/jobs/data-analytics-jobs | K35: USD-denominated onsite role | L35: Lahore | M35: Onsite | N35: Not disclosed | O35: Not disclosed | P35: No | Q35: 2026-06-01 | U35: data analyst (onsite lahore) | usd-denominated onsite role | technology
A36: Data Scientist | B36: Confidential | C36: Karachi | D36: Technology | E36: Not disclosed | F36: Not disclosed | G36: Not disclosed | H36: LinkedIn | I36: 2026-06 | J36: https://pk.linkedin.com/jobs/data-analytics-jobs | K36: Actively hiring | L36: Karachi | M36: Not disclosed | N36: Not disclosed | O36: Not disclosed | P36: No | Q36: 2026-06-01 | U36: data scientist | actively hiring | technology
A37: Assistant Manager - Data Analytics | B37: Confidential | C37: Karachi | D37: Technology | E37: Not disclosed | F37: Assistant Manager | G37: Not disclosed | H37: LinkedIn | I37: 2026-06 | J37: https://pk.linkedin.com/jobs/data-analysis-jobs | K37: Actively hiring | L37: Karachi | M37: Not disclosed | N37: Not disclosed | O37: Senior | P37: No | Q37: 2026-06-01 | U37: assistant manager - data analytics | actively hiring | technology
A38: Trainee Data Science | B38: Confidential | C38: Lahore | D38: Technology | E38: Trainee | F38: Entry level | G38: Not disclosed | H38: LinkedIn | I38: 2026-06 | J38: https://pk.linkedin.com/jobs/data-analysis-jobs | L38: Lahore | M38: Not disclosed | N38: Trainee | O38: Entry/Fresh | P38: No | Q38: 2026-06-01 | U38: trainee data science | | technology
A39: Business Analyst - Agri | B39: Confidential | C39: Karachi | D39: Agriculture | E39: Not disclosed | F39: Not disclosed | G39: Not disclosed | H39: LinkedIn | I39: 2026-06 | J39: https://pk.linkedin.com/jobs/data-analysis-jobs | K39: Actively hiring | L39: Karachi | M39: Not disclosed | N39: Not disclosed | O39: Not disclosed | P39: No | Q39: 2026-06-01 | U39: business analyst - agri | actively hiring | agriculture
A40: Data Scientist | B40: Habib Bank AG Zurich | C40: Karachi | D40: Banking | E40: Not disclosed | F40: Not disclosed | G40: Not disclosed | H40: LinkedIn | I40: 2026-04-14 | J40: https://pk.linkedin.com/jobs/view/data-scientist-at-habib-bank-ag-zurich-4399532611 | K40: Individual job posting URL | L40: Karachi | M40: Not disclosed | N40: Not disclosed | O40: Not disclosed | P40: No | Q40: 2026-04-14 | U40: data scientist | individual job posting url | banking
A41: Data Scientist (Oil & Gas Industry) | B41: CodeByte (client) | C41: Lahore | D41: Oil & Gas | E41: Contract (min 1 yr) | F41: 5-8 years | G41: USD 2500-3000/month | H41: BeBee | I41: 2026-05 | J41: https://bebee.com/pk/jobs/role/data-scientist | K41: Department: Digital Transformation / Data & Analytics | L41: Lahore | M41: Not disclosed | N41: Contract | O41: Senior | P41: Yes | Q41: 2026-05-01 | R41: USD | S41: 2750 | U41: data scientist (oil & gas industry) | department: digital transformation / data & analytics | oil & gas
A42: Deep Learning Specialist | B42: Translation Empire PK | C42: Not disclosed | D42: IT Services | E42: Not disclosed | F42: Not disclosed | G42: Not disclosed | H42: BeBee | I42: 2026-05 | J42: https://bebee.com/pk/jobs/role/data-scientist | K42: Image/text/signal data models | L42: Not disclosed | M42: Not disclosed | N42: Not disclosed | O42: Not disclosed | P42: No | Q42: 2026-05-01 | U42: deep learning specialist | image/text/signal data models | it services
A43: NLP Engineer | B43: Translation Empire PK | C43: Not disclosed | D43: IT Services | E43: Not disclosed | F43: Not disclosed | G43: Not disclosed | H43: BeBee | I43: 2026-05 | J43: https://bebee.com/pk/jobs/role/data-scientist | K43: Text classification, sentiment analysis | L43: Not disclosed | M43: Not disclosed | N43: Not disclosed | O43: Not disclosed | P43: No | Q43: 2026-05-01 | U43: nlp engineer | text classification, sentiment analysis | it services
A44: Analytics Engineer / BI Engineer | B44: Confidential (UK consultancy client) | C44: Karachi | D44: Consulting | E44: Hybrid | F44: Not disclosed | G44: Not disclosed | H44: BeBee | I44: 2026-05 | J44: https://bebee.com/pk/jobs/role/data-scientist | K44: Reporting & Data Platform | L44: Karachi | M44: Hybrid | N44: Not disclosed | O44: Not disclosed | P44: No | Q44: 2026-05-01 | U44: analytics engineer / bi engineer | reporting & data platform | consulting
A45: Senior Data Scientist | B45: NorthBay | C45: Karachi | D45: Technology | E45: Hybrid, Full-time | F45: 8+ years | G45: Not disclosed | H45: BeBee | I45: 2026-05 | J45: https://bebee.com/pk/jobs/role/data-scientist | K45: Data processing and visualization focus | L45: Karachi | M45: Hybrid | N45: Full-time | O45: Senior | P45: No | Q45: 2026-05-01 | U45: senior data scientist | data processing and visualization focus | technology
A46: Data Scientist (Machine Learning) | B46: Tata Consultancy Services | C46: Pakistan | D46: IT Services | E46: Not disclosed | F46: 5+ years | G46: Not disclosed | H46: Glassdoor | I46: 2026-05 | J46: https://www.glassdoor.com/Job/data-scientist-jobs-SRCH_IN192_KO0,14.htm | K46: Time series forecasting, anomaly detection | L46: Remote/Unspecified | M46: Not disclosed | N46: Not disclosed | O46: Senior | P46: No | Q46: 2026-05-01 | U46: data scientist (machine learning) | time series forecasting, anomaly detection | it services
A47: Data Scientist | B47: Fortray Global Services | C47: Pakistan | D47: IT Services | E47: Not disclosed | F47: Not disclosed | G47: Not disclosed | H47: Glassdoor | I47: 2026-05 | J47: https://www.glassdoor.com/Job/data-scientist-jobs-SRCH_IN192_KO0,14.htm | K47: Project planning, data collection & cleaning | L47: Remote/Unspecified | M47: Not disclosed | N47: Not disclosed | O47: Not disclosed | P47: No | Q47: 2026-05-01 | U47: data scientist | project planning, data collection & cleaning | it services
A48: Data Scientist/ML Engineer | B48: Soothsayer Analytics | C48: Pakistan | D48: Analytics | E48: Not disclosed | F48: Not disclosed | G48: Not disclosed | H48: Glassdoor | I48: 2026-05 | J48: https://www.glassdoor.com/Job/data-scientist-jobs-SRCH_IN192_KO0,14.htm | K48: Python data processing | L48: Remote/Unspecified | M48: Not disclosed | N48: Not disclosed | O48: Not disclosed | P48: No | Q48: 2026-05-01 | U48: data scientist/ml engineer | python data processing | analytics
A49: AI/Responsible AI Collaborator | B49: CureMD | C49: Pakistan | D49: HealthTech | E49: Not disclosed | F49: Not disclosed | G49: Not disclosed | H49: Glassdoor | I49: 2026-05 | J49: https://www.glassdoor.com/Job/data-scientist-jobs-SRCH_IN192_KO0,14.htm | K49: Clinical experts + data scientists collaboration | L49: Remote/Unspecified | M49: Not disclosed | N49: Not disclosed | O49: Not disclosed | P49: No | Q49: 2026-05-01 | U49: ai/responsible ai collaborator | clinical experts + data scientists collaboration | healthtech
A50: Data Collection Specialist | B50: DM Clinical Research | C50: Pakistan | D50: Healthcare Research | E50: Not disclosed | F50: Not disclosed | G50: Not disclosed | H50: Glassdoor | I50: 2026-05 | J50: https://www.glassdoor.com/Job/data-scientist-jobs-SRCH_IN192_KO0,14.htm | K50: Model training operations support | L50: Remote/Unspecified | M50: Not disclosed | N50: Not disclosed | O50: Not disclosed | P50: No | Q50: 2026-05-01 | U50: data collection specialist | model training operations support | healthcare research
A51: Python Developer - Machine Learning | B51: King Revolution Inc | C51: Pakistan | D51: IT Services | E51: Not disclosed | F51: Not disclosed | G51: Not disclosed | H51: Glassdoor | I51: 2026-05 | J51: https://www.glassdoor.com/Job/data-scientist-jobs-SRCH_IN192_KO0,14.htm | K51: Large dataset preprocessing | L51: Remote/Unspecified | M51: Not disclosed | N51: Not disclosed | O51: Not disclosed | P51: No | Q51: 2026-05-01 | U51: python developer - machine learning | large dataset preprocessing | it services
A52: Senior Power BI Developer | B52: VentureDive | C52: Karachi | D52: IT Services | E52: Not disclosed | F52: 8+ years | G52: Not disclosed | H52: Indeed Pakistan | I52: 2026-06-01 | J52: https://pk.indeed.com/q-power-bi-developer-l-karachi-jobs.html | K52: PL-300 / DP-500 certification preferred | L52: Karachi | M52: Not disclosed | N52: Not disclosed | O52: Senior | P52: No | Q52: 2026-06-01 | U52: senior power bi developer | pl-300 / dp-500 certification preferred | it services
A53: Data Analyst - Mid level (Urgent) | B53: Ibix Global Tech | C53: Karachi | D53: IT Services | E53: Not disclosed | F53: Mid level | G53: Not disclosed | H53: Indeed Pakistan | I53: 2026-06-01 | J53: https://pk.indeed.com/q-power-bi-l-karachi-jobs.html | L53: Karachi | M53: Not disclosed | N53: Not disclosed | O53: Mid | P53: No | Q53: 2026-06-01 | U53: data analyst - mid level (urgent) | | it services
A54: Power BI Developer | B54: Systems Limited | C54: Karachi | D54: IT Services | E54: Not disclosed | F54: Not disclosed | G54: Not disclosed | H54: Indeed Pakistan | I54: 2026-06-01 | J54: https://pk.indeed.com/q-power-bi-l-karachi-jobs.html | K54: End-to-end dashboard lifecycle | L54: Karachi | M54: Not disclosed | N54: Not disclosed | O54: Not disclosed | P54: No | Q54: 2026-06-01 | U54: power bi developer | end-to-end dashboard lifecycle | it services
A55: Data & Reporting Analyst | B55: PwC | C55: Karachi | D55: Consulting | E55: Not disclosed | F55: Not disclosed | G55: Not disclosed | H55: Indeed Pakistan | I55: 2026-06-01 | J55: https://pk.indeed.com/q-power-bi-l-karachi-jobs.html | L55: Karachi | M55: Not disclosed | N55: Not disclosed | O55: Not disclosed | P55: No | Q55: 2026-06-01 | U55: data & reporting analyst | | consulting
A56: Data Analysis - Production Insights | B56: Ana & Batla Industries Pvt Ltd | C56: Karachi (Landhi Colony) | D56: Manufacturing | E56: Not disclosed | F56: Not disclosed | G56: Not disclosed | H56: Indeed Pakistan | I56: 2026-06-01 | J56: https://pk.indeed.com/q-power-bi-l-karachi-jobs.html | K56: Mon-Fri 9-6, Sat 9-1 | L56: Karachi | M56: Not disclosed | N56: Not disclosed | O56: Not disclosed | P56: No | Q56: 2026-06-01 | U56: data analysis - production insights | mon-fri 9-6, sat 9-1 | manufacturing
A57: Data Analyst - Apparel Retail | B57: Garments company (name withheld in listing) | C57: Karachi | D57: Retail/Apparel | E57: Not disclosed | F57: 3-5 years | G57: Not disclosed | H57: Indeed Pakistan | I57: 2026-06-01 | J57: https://pk.indeed.com/q-power-bi-l-karachi-jobs.html | K57: Bachelor's in Data Science/Statistics/Business Analytics preferred | L57: Karachi | M57: Not disclosed | N57: Not disclosed | O57: Mid | P57: No | Q57: 2026-06-01 | U57: data analyst - apparel retail | bachelor's in data science/statistics/business analytics preferred | retail/apparel
A58: Research Intern | B58: Louis Dreyfus Company | C58: Karachi | D58: Agri-Commodities | E58: Internship | F58: Student/fresh grad | G58: Not disclosed | H58: Indeed Pakistan | I58: 2026-06-01 | J58: https://pk.indeed.com/q-power-bi-l-karachi-jobs.html | L58: Karachi | M58: Not disclosed | N58: Internship | O58: Entry/Fresh | P58: No | Q58: 2026-06-01 | U58: research intern | | agri-commodities
A59: Software Developer | B59: Aga Khan Health Service Pakistan | C59: Karachi | D59: Healthcare | E59: Not disclosed | F59: Not disclosed | G59: Not disclosed | H59: Indeed Pakistan | I59: 2026-05-11 | J59: https://pk.indeed.com/q-power-bi-l-karachi-gulshan-e-iqbal-jobs.html | L59: Karachi | M59: Not disclosed | N59: Not disclosed | O59: Not disclosed | P59: No | Q59: 2026-05-11 | U59: software developer | | healthcare
A60: Power BI Developer / BI Analyst | B60: Ibix Global Tech | C60: Karachi | D60: IT Services | E60: Not disclosed | F60: 2-4 years | G60: Not disclosed | H60: Indeed Pakistan | I60: 2026-05-11 | J60: https://pk.indeed.com/q-power-bi-l-karachi-gulshan-e-iqbal-jobs.html | L60: Karachi | M60: Not disclosed | N60: Not disclosed | O60: Mid | P60: No | Q60: 2026-05-11 | U60: power bi developer / bi analyst | | it services
A61: Senior Power BI Developer | B61: Pivotize Consulting | C61: Karachi | D61: Consulting | E61: Not disclosed | F61: Not disclosed | G61: Not disclosed | H61: Indeed Pakistan | I61: 2026-05-11 | J61: https://pk.indeed.com/q-power-bi-l-karachi-gulshan-e-iqbal-jobs.html | K61: BI team member | L61: Karachi | M61: Not disclosed | N61: Not disclosed | O61: Not disclosed | P61: No | Q61: 2026-05-11 | U61: senior power bi developer | bi team member | consulting
A62: Power BI Business Intelligence Analyst | B62: Provox Global Solutions | C62: Pakistan (Remote) | D62: Consulting | E62: Remote | F62: Not disclosed | G62: Not disclosed | H62: Indeed Pakistan | I62: 2026-06-25 | J62: https://pk.indeed.com/q-bi-business-intelligence-analyst-jobs.html | K62: Fire protection services client; QuickBooks + Inspect Point data | L62: Remote/Unspecified | M62: Remote | N62: Not disclosed | O62: Not disclosed | P62: No | Q62: 2026-06-25 | U62: power bi business intelligence analyst | fire protection services client; quickbooks + inspect point data | consulting
A63: Business Intelligence Analyst | B63: Jeeny | C63: Lahore | D63: Ride-hailing/Tech | E63: Not disclosed | F63: Not disclosed | G63: Not disclosed | H63: Indeed Pakistan | I63: 2026-06-25 | J63: https://pk.indeed.com/q-bi-business-intelligence-analyst-jobs.html | L63: Lahore | M63: Not disclosed | N63: Not disclosed | O63: Not disclosed | P63: No | Q63: 2026-06-25 | U63: business intelligence analyst | | ride-hailing/tech
A64: Business Intelligence Developer | B64: BGBx | C64: Pakistan | D64: Technology | E64: Not disclosed | F64: Not disclosed | G64: Not disclosed | H64: Indeed Pakistan | I64: 2026-06-25 | J64: https://pk.indeed.com/q-bi-business-intelligence-analyst-jobs.html | L64: Remote/Unspecified | M64: Not disclosed | N64: Not disclosed | O64: Not disclosed | P64: No | Q64: 2026-06-25 | U64: business intelligence developer | | technology
A65: Microsoft Power BI Developer | B65: Müller's Solutions | C65: Islamabad | D65: IT Services | E65: Not disclosed | F65: Not disclosed | G65: Not disclosed | H65: Indeed Pakistan | I65: 2026-06-25 | J65: https://pk.indeed.com/q-bi-business-intelligence-analyst-jobs.html | L65: Islamabad | M65: Not disclosed | N65: Not disclosed | O65: Not disclosed | P65: No | Q65: 2026-06-25 | U65: microsoft power bi developer | | it services
A66: BI Developer | B66: MTBC | C66: Rawalpindi | D66: Healthcare IT | E66: Not disclosed | F66: Not disclosed | G66: Not disclosed | H66: Indeed Pakistan | I66: 2026-06-25 | J66: https://pk.indeed.com/q-bi-business-intelligence-analyst-jobs.html | K66: 24-hour SLA ad hoc decision support | L66: Rawalpindi | M66: Not disclosed | N66: Not disclosed | O66: Not disclosed | P66: No | Q66: 2026-06-25 | U66: bi developer | 24-hour sla ad hoc decision support | healthcare it
A67: Business Intelligence Developer | B67: Systems Limited | C67: Karachi | D67: IT Services | E67: Not disclosed | F67: Not disclosed | G67: Not disclosed | H67: Indeed Pakistan | I67: 2026-06-25 | J67: https://pk.indeed.com/q-bi-business-intelligence-analyst-jobs.html | L67: Karachi | M67: Not disclosed | N67: Not disclosed | O67: Not disclosed | P67: No | Q67: 2026-06-25 | U67: business intelligence developer | | it services
A68: Power BI Developer | B68: HRSG SSP | C68: Sahiwal | D68: IT Services | E68: Not disclosed | F68: Not disclosed | G68: Not disclosed | H68: Indeed Pakistan | I68: 2026-06-25 | J68: https://pk.indeed.com/q-bi-business-intelligence-analyst-jobs.html | L68: Sahiwal | M68: Not disclosed | N68: Not disclosed | O68: Not disclosed | P68: No | Q68: 2026-06-25 | U68: power bi developer | | it services
A69: Business Intelligence Developer | B69: Lloyds Technology Centre | C69: Hyderabad | D69: Banking/Fintech | E69: Not disclosed | F69: Not disclosed | G69: Not disclosed | H69: Indeed Pakistan | I69: 2026-06-25 | J69: https://pk.indeed.com/q-bi-business-intelligence-analyst-jobs.html | K69: DAX measures, KPI time-intelligence | L69: Hyderabad | M69: Not disclosed | N69: Not disclosed | O69: Not disclosed | P69: No | Q69: 2026-06-25 | U69: business intelligence developer | dax measures, kpi time-intelligence | banking/fintech
A70: Dynamics 365 Developer (Power BI Experience) | B70: H2O Labs | C70: Lahore (Johar Town) | D70: IT Services | E70: Not disclosed | F70: Not disclosed | G70: Not disclosed | H70: Indeed Pakistan | I70: 2026-06-25 | J70: https://pk.indeed.com/q-bi-business-intelligence-analyst-jobs.html | L70: Lahore | M70: Not disclosed | N70: Not disclosed | O70: Not disclosed | P70: No | Q70: 2026-06-25 | U70: dynamics 365 developer (power bi experience) | | it services
A71: Financial & Data Analyst | B71: Pavago (client) | C71: Pakistan (Remote) | D71: Consulting | E71: Full-time, Remote | F71: Not disclosed | G71: Not disclosed | H71: Indeed Pakistan | I71: 2025-12-22 | J71: https://pk.indeed.com/q-power-bi-jobs.html | K71: US client business hours | L71: Remote/Unspecified | M71: Remote | N71: Full-time | O71: Not disclosed | P71: No | Q71: 2025-12-22 | U71: financial & data analyst | us client business hours | consulting
A72: Full Stack Developer - PostgreSQL/Big Data/AI | B72: The Garcia Team | C72: Pakistan (Remote) | D72: IT Services | E72: Remote | F72: Not disclosed | G72: Not disclosed | H72: Indeed Pakistan | I72: 2025-12-22 | J72: https://pk.indeed.com/q-power-bi-jobs.html | K72: 100M+ records processing | L72: Remote/Unspecified | M72: Remote | N72: Not disclosed | O72: Not disclosed | P72: No | Q72: 2025-12-22 | U72: full stack developer - postgresql/big data/ai | 100m+ records processing | it services
A73: Digital Business Analyst | B73: Confidential | C73: Lahore (Remote) | D73: IT Services | E73: Full-time, Remote | F73: Not disclosed | G73: Not disclosed | H73: Indeed Pakistan | I73: 2025-12-22 | J73: https://pk.indeed.com/q-power-bi-jobs.html | K73: US client business hours | L73: Lahore | M73: Remote | N73: Full-time | O73: Not disclosed | P73: No | Q73: 2025-12-22 | U73: digital business analyst | us client business hours | it services
A74: AI & Data Science Strategy Associate Consultant | B74: Ontrac Solutions | C74: Karachi | D74: Consulting | E74: Not disclosed | F74: Mid-level | G74: Not disclosed | H74: Indeed Pakistan | I74: 2025-12-22 | J74: https://pk.indeed.com/q-power-bi-jobs.html | L74: Karachi | M74: Not disclosed | N74: Not disclosed | O74: Mid | P74: No | Q74: 2025-12-22 | U74: ai & data science strategy associate consultant | | consulting
A75: Data Analyst | B75: Robust Support & Solutions | C75: Karachi | D75: IT Services | E75: Not disclosed | F75: Not disclosed | G75: Not disclosed | H75: Glassdoor | I75: 2026-06 | J75: https://www.glassdoor.com/Job/kar%C4%81chi-power-bi-jobs-SRCH_IL.0,7_IC3212296_KO8,16.htm | L75: Karachi | M75: Not disclosed | N75: Not disclosed | O75: Not disclosed | P75: No | Q75: 2026-06-01 | U75: data analyst | | it services
A76: Production Reporting Specialist (Data Analysis) | B76: Ana & Batla Industries Pvt Ltd | C76: Karachi (Landhi Colony) | D76: Manufacturing | E76: Not disclosed | F76: Not disclosed | G76: Not disclosed | H76: Glassdoor | I76: 2026-06 | J76: https://www.glassdoor.com/Job/kar%C4%81chi-power-bi-jobs-SRCH_IL.0,7_IC3212296_KO8,16.htm | L76: Karachi | M76: Not disclosed | N76: Not disclosed | O76: Not disclosed | P76: No | Q76: 2026-06-01 | U76: production reporting specialist (data analysis) | | manufacturing
A77: Sr. Power BI Developer (Remote) | B77: Code Creators | C77: Pakistan (Remote) | D77: IT Services | E77: Remote | F77: 3+ years | G77: Not disclosed | H77: Glassdoor | I77: 2025-10 | J77: https://www.glassdoor.com/Job/pakistan-bi-jobs-SRCH_IL.0,8_IN192_KO9,11.htm | L77: Remote/Unspecified | M77: Remote | N77: Not disclosed | O77: Mid | P77: No | Q77: 2025-10-01 | U77: sr. power bi developer (remote) | | it services
A78: Power BI Expert | B78: Aricrypta | C78: Pakistan | D78: Fintech/Crypto | E78: Not disclosed | F78: Not disclosed | G78: Not disclosed | H78: Glassdoor | I78: 2025-10 | J78: https://www.glassdoor.com/Job/pakistan-bi-jobs-SRCH_IL.0,8_IN192_KO9,11.htm | L78: Remote/Unspecified | M78: Not disclosed | N78: Not disclosed | O78: Not disclosed | P78: No | Q78: 2025-10-01 | U78: power bi expert | | fintech/crypto
A79: Data Analyst | B79: Careem | C79: Pakistan | D79: Ride-hailing/Tech | E79: Not disclosed | F79: Not disclosed | G79: Not disclosed | H79: Glassdoor | I79: 2025-10 | J79: https://www.glassdoor.com/Job/pakistan-bi-jobs-SRCH_IL.0,8_IN192_KO9,11.htm | K79: Careem Analytics team | L79: Remote/Unspecified | M79: Not disclosed | N79: Not disclosed | O79: Not disclosed | P79: No | Q79: 2025-10-01 | U79: data analyst | careem analytics team | ride-hailing/tech
A80: Junior Data Engineer (SQL/ETL) | B80: Prima Systems | C80: Lahore | D80: IT Services | E80: Not disclosed | F80: Junior | G80: Not disclosed | H80: Indeed Pakistan | I80: 2026-06-02 | J80: https://pk.indeed.com/q-data-engineer-jobs.html | L80: Lahore | M80: Not disclosed | N80: Not disclosed | O80: Entry/Fresh | P80: No | Q80: 2026-06-02 | U80: junior data engineer (sql/etl) | | it services
A81: Python Engineer | B81: Tata Consultancy Services | C81: Hyderabad | D81: IT Services | E81: Not disclosed | F81: Not disclosed | G81: Not disclosed | H81: Indeed Pakistan | I81: 2026-06-02 | J81: https://pk.indeed.com/q-data-engineer-jobs.html | K81: AI Superleague accelerated track | L81: Hyderabad | M81: Not disclosed | N81: Not disclosed | O81: Not disclosed | P81: No | Q81: 2026-06-02 | U81: python engineer | ai superleague accelerated track | it services
A82: Associate Data Engineer | B82: 9D Technologies & Imagination AI | C82: Rawalpindi | D82: IT Services | E82: Not disclosed | F82: Not disclosed | G82: Not disclosed | H82: Indeed Pakistan | I82: 2026-06-02 | J82: https://pk.indeed.com/q-data-engineer-jobs.html | L82: Rawalpindi | M82: Not disclosed | N82: Not disclosed | O82: Not disclosed | P82: No | Q82: 2026-06-02 | U82: associate data engineer | | it services
A83: Senior Data Engineer | B83: Aegasis Labs | C83: Lahore | D83: IT Services | E83: Not disclosed | F83: Senior | G83: Not disclosed | H83: Indeed Pakistan | I83: 2026-06-02 | J83: https://pk.indeed.com/q-data-engineer-jobs.html | K83: AWS/Azure/GCP experience | L83: Lahore | M83: Not disclosed | N83: Not disclosed | O83: Senior | P83: No | Q83: 2026-06-02 | U83: senior data engineer | aws/azure/gcp experience | it services
A84: Data Engineer (Adobe AEP) | B84: TechBiz Global GmbH | C84: Islamabad | D84: IT Services | E84: Not disclosed | F84: Not disclosed | G84: Not disclosed | H84: Indeed Pakistan | I84: 2026-06-19 | J84: https://pk.indeed.com/q-data-engineer-l-islamabad-jobs.html | L84: Islamabad | M84: Not disclosed | N84: Not disclosed | O84: Not disclosed | P84: No | Q84: 2026-06-19 | U84: data engineer (adobe aep) | | it services
A85: Data Engineer | B85: Python Technologies | C85: Islamabad | D85: IT Services | E85: Not disclosed | F85: Not disclosed | G85: Not disclosed | H85: Indeed Pakistan | I85: 2026-06-19 | J85: https://pk.indeed.com/q-data-engineer-l-islamabad-jobs.html | L85: Islamabad | M85: Not disclosed | N85: Not disclosed | O85: Not disclosed | P85: No | Q85: 2026-06-19 | U85: data engineer | | it services
A86: Data Engineer | B86: International Rescue Committee | C86: Islamabad | D86: NGO | E86: Not disclosed | F86: Not disclosed | G86: Not disclosed | H86: Indeed Pakistan | I86: 2026-06-19 | J86: https://pk.indeed.com/q-data-engineer-l-islamabad-jobs.html | L86: Islamabad | M86: Not disclosed | N86: Not disclosed | O86: Not disclosed | P86: No | Q86: 2026-06-19 | U86: data engineer | | ngo
A87: Data Engineer | B87: Datamatics Technologies | C87: Islamabad | D87: IT Services | E87: Not disclosed | F87: Not disclosed | G87: Not disclosed | H87: Indeed Pakistan | I87: 2026-06-19 | J87: https://pk.indeed.com/q-data-engineer-l-islamabad-jobs.html | K87: ETL/ELT workflows | L87: Islamabad | M87: Not disclosed | N87: Not disclosed | O87: Not disclosed | P87: No | Q87: 2026-06-19 | U87: data engineer | etl/elt workflows | it services
A88: Senior Data Engineer | B88: Trickle Up | C88: Rawalpindi | D88: NGO/Development | E88: Not disclosed | F88: Senior | G88: Not disclosed | H88: Indeed Pakistan | I88: 2026-06-19 | J88: https://pk.indeed.com/q-data-engineer-l-islamabad-jobs.html | K88: Data warehouse and lake design | L88: Rawalpindi | M88: Not disclosed | N88: Not disclosed | O88: Senior | P88: No | Q88: 2026-06-19 | U88: senior data engineer | data warehouse and lake design | ngo/development
A89: Data Engineer | B89: Darkroom | C89: Islamabad | D89: Marketing Tech | E89: Not disclosed | F89: Not disclosed | G89: Not disclosed | H89: Indeed Pakistan | I89: 2026-06-19 | J89: https://pk.indeed.com/q-data-engineer-l-islamabad-jobs.html | L89: Islamabad | M89: Not disclosed | N89: Not disclosed | O89: Not disclosed | P89: No | Q89: 2026-06-19 | U89: data engineer | | marketing tech
A90: Senior Data Engineer & Data Architect | B90: TechBiz Global GmbH | C90: Islamabad | D90: IT Services | E90: Not disclosed | F90: 15+ years | G90: Not disclosed | H90: Indeed Pakistan | I90: 2026-06-19 | J90: https://pk.indeed.com/q-data-engineer-l-islamabad-jobs.html | K90: Data governance and catalog tools | L90: Islamabad | M90: Not disclosed | N90: Not disclosed | O90: Senior | P90: No | Q90: 2026-06-19 | U90: senior data engineer & data architect | data governance and catalog tools | it services
A91: Data Engineer | B91: Macquarie Group Limited | C91: Pakistan | D91: Financial Services | E91: Not disclosed | F91: Not disclosed | G91: Not disclosed | H91: Glassdoor | I91: 2026-03 | J91: https://www.glassdoor.com/Job/pakistan-data-engineer-jobs-SRCH_IL.0,8_IN192_KO9,22.htm | K91: Global financial services group, 31 markets | L91: Remote/Unspecified | M91: Not disclosed | N91: Not disclosed | O91: Not disclosed | P91: No | Q91: 2026-03-01 | U91: data engineer | global financial services group, 31 markets | financial services
A92: Data Engineer | B92: Capgemini | C92: Pakistan | D92: IT Consulting | E92: Not disclosed | F92: Not disclosed | G92: Not disclosed | H92: Glassdoor | I92: 2026-03 | J92: https://www.glassdoor.com/Job/pakistan-data-engineer-jobs-SRCH_IL.0,8_IN192_KO9,22.htm | L92: Remote/Unspecified | M92: Not disclosed | N92: Not disclosed | O92: Not disclosed | P92: No | Q92: 2026-03-01 | U92: data engineer | | it consulting
A93: Data Engineer | B93: Lloyds Technology Centre | C93: Pakistan | D93: Banking/Fintech | E93: Not disclosed | F93: Not disclosed | G93: Not disclosed | H93: Glassdoor | I93: 2026-03 | J93: https://www.glassdoor.com/Job/pakistan-data-engineer-jobs-SRCH_IL.0,8_IN192_KO9,22.htm | L93: Remote/Unspecified | M93: Not disclosed | N93: Not disclosed | O93: Not disclosed | P93: No | Q93: 2026-03-01 | U93: data engineer | | banking/fintech
A94: Data Engineer | B94: TCP Software | C94: Pakistan | D94: IT Services | E94: Not disclosed | F94: Not disclosed | G94: Not disclosed | H94: Glassdoor | I94: 2026-03 | J94: https://www.glassdoor.com/Job/pakistan-data-engineer-jobs-SRCH_IL.0,8_IN192_KO9,22.htm | L94: Remote/Unspecified | M94: Not disclosed | N94: Not disclosed | O94: Not disclosed | P94: No | Q94: 2026-03-01 | U94: data engineer | | it services
A95: Data Engineer | B95: Contour Software | C95: Pakistan | D95: IT Services | E95: Not disclosed | F95: Not disclosed | G95: Not disclosed | H95: Glassdoor | I95: 2026-03 | J95: https://www.glassdoor.com/Job/pakistan-data-engineer-jobs-SRCH_IL.0,8_IN192_KO9,22.htm | L95: Remote/Unspecified | M95: Not disclosed | N95: Not disclosed | O95: Not disclosed | P95: No | Q95: 2026-03-01 | U95: data engineer | | it services
A96: Data Engineer | B96: InvoZone | C96: Pakistan | D96: IT Services | E96: Not disclosed | F96: Not disclosed | G96: Not disclosed | H96: Glassdoor | I96: 2026-03 | J96: https://www.glassdoor.com/Job/pakistan-data-engineer-jobs-SRCH_IL.0,8_IN192_KO9,22.htm | L96: Remote/Unspecified | M96: Not disclosed | N96: Not disclosed | O96: Not disclosed | P96: No | Q96: 2026-03-01 | U96: data engineer | | it services
A97: Data Engineer | B97: Tech Bridge Consultancy | C97: Pakistan | D97: Consulting | E97: Not disclosed | F97: Not disclosed | G97: Not disclosed | H97: Glassdoor | I97: 2026-03 | J97: https://www.glassdoor.com/Job/pakistan-data-engineer-jobs-SRCH_IL.0,8_IN192_KO9,22.htm | L97: Remote/Unspecified | M97: Not disclosed | N97: Not disclosed | O97: Not disclosed | P97: No | Q97: 2026-03-01 | U97: data engineer | | consulting
A98: Data Engineer | B98: Aqovia | C98: Pakistan | D98: IT Services | E98: Not disclosed | F98: Not disclosed | G98: Not disclosed | H98: Glassdoor | I98: 2026-03 | J98: https://www.glassdoor.com/Job/pakistan-data-engineer-jobs-SRCH_IL.0,8_IN192_KO9,22.htm | L98: Remote/Unspecified | M98: Not disclosed | N98: Not disclosed | O98: Not disclosed | P98: No | Q98: 2026-03-01 | U98: data engineer | | it services
A99: Associate Data Engineer | B99: PostEx | C99: Lahore | D99: Logistics/Fintech | E99: Not disclosed | F99: Associate | G99: Not disclosed | H99: BeBee | I99: 2026-04-21 | J99: https://bebee.com/pk/jobs/role/data-engineer | K99: SQL and Data Warehousing | L99: Lahore | M99: Not disclosed | N99: Not disclosed | O99: Mid | P99: No | Q99: 2026-04-21 | U99: associate data engineer | sql and data warehousing | logistics/fintech
A100: Data Engineer - Infrastructure (Remote/Contract) | B100: Confidential client | C100: Pakistan (Remote) | D100: IT Services | E100: Contract | F100: Not disclosed | G100: USD 30-100/hour | H100: BeBee | I100: 2026-04-21 | J100: https://bebee.com/pk/jobs/role/data-engineer | K100: Work from anywhere | L100: Remote/Unspecified | M100: Not disclosed | N100: Contract | O100: Not disclosed | P100: Yes | Q100: 2026-04-21 | T100: Hourly rate (excluded from monthly avg) | U100: data engineer - infrastructure (remote/contract) | work from anywhere | it services
...

Sheet Macro_Context_PBS
A1: National Labour Market Context (Official PBS Data)
A3: Indicator | B3: Value | C3: Unit | D3: Period | E3: Source
A4: Overall unemployment rate | B4: 6.9 | C4: percent | D4: 2024-25 | E4: Pakistan Bureau of Statistics - Labour Force Survey 2024-25
A5: Previous unemployment rate | B5: 6.3 | C5: percent | D5: 2020-21 | E5: Pakistan Bureau of Statistics - Labour Force Survey 2020-21
A6: Female unemployment rate | B6: 9.7 | C6: percent | D6: 2024-25 | E6: Pakistan Bureau of Statistics - Labour Force Survey 2024-25
A7: Labour Force Participation Rate (LFPR) | B7: 47.7 | C7: percent | D7: 2024-25 | E7: Pakistan Bureau of Statistics - Labour Force Survey 2024-25 (13th ICLS)
A8: Previous LFPR | B8: 44.9 | C8: percent | D8: 2020-21 | E8: Pakistan Bureau of Statistics - Labour Force Survey 2020-21
A9: Services sector share of employment | B9: 41.2 | C9: percent | D9: 2024 | E9: Government of Pakistan - Planning Commission press release
A10: Agriculture sector share of employment | B10: 33.1 | C10: percent | D10: 2024 | E10: Government of Pakistan - Planning Commission press release
A11: Previous agriculture sector share | B11: 37.4 | C11: percent | D11: 2021 | E11: Government of Pakistan - Planning Commission press release
A12: Average monthly wage | B12: 39000 | C12: PKR | D12: 2024-25 | E12: Government of Pakistan - Planning Commission press release
A13: Previous average monthly wage | B13: 24000 | C13: PKR | D13: 2013 baseline | E13: Government of Pakistan - Planning Commission press release
A14: Gender wage gap | B14: 2000 | C14: PKR per month | D14: 2024-25 | E14: Government of Pakistan - Planning Commission press release
A15: Previous gender wage gap | B15: 4500 | C15: PKR per month | D15: 2020-21 | E15: Government of Pakistan - Planning Commission press release
... A18: Households surveyed for LFS 2024-25 | B18: 54000 | C18: households | D18: 2024-25 | E18: Pakistan Bureau of Statistics - Labour Force Survey 2024-25
A20: Sample vs National Comparison
A21: Metric | B21: Our Sample (155 listings) | C21: Context / Note
A22: Salary transparency (% listings disclosing salary in any form) | B22: =COUNTIF(Cleaned_Data!P2:P156,"Yes")/COUNTA(Cleaned_Data!P2:P156) -> 0.025806452 | C22: Reflects same wage-opacity pattern as Pakistan's large informal labour sector (agriculture 33.1% + informal services)

Sheet Summary_City
A1: City-wise Job Listing Distribution
A3: City | B3: Number of Listings
A4: Karachi | B4: =COUNTIF(Cleaned_Data!L2:L156,A4) -> 43
A5: Lahore | B5: =COUNTIF(Cleaned_Data!L2:L156,A5) -> 35
A6: Remote/Unspecified | B6: =COUNTIF(Cleaned_Data!L2:L156,A6) -> 34
A7: Islamabad | B7: =COUNTIF(Cleaned_Data!L2:L156,A7) -> 16
A8: Not disclosed | B8: =COUNTIF(Cleaned_Data!L2:L156,A8) -> 9
A9: Rawalpindi | B9: =COUNTIF(Cleaned_Data!L2:L156,A9) -> 5
A10: Hyderabad | B10: =COUNTIF(Cleaned_Data!L2:L156,A10) -> 4
A11: Multi-city | B11: =COUNTIF(Cleaned_Data!L2:L156,A11) -> 3
A12: Faisalabad | B12: =COUNTIF(Cleaned_Data!L2:L156,A12) -> 3
A13: Multan | B13: =COUNTIF(Cleaned_Data!L2:L156,A13) -> 1
A14: Punjab (unspecified city) | B14: =COUNTIF(Cleaned_Data!L2:L156,A14) -> 1
A15: Sahiwal | B15: =COUNTIF(Cleaned_Data!L2:L156,A15) -> 1
A16: Total | B16: =SUM(B4:B15) -> 155

Sheet Summary_Platform
A1: Platform-wise Listing Source
A3: Platform | B3: Number of Listings
A4: Indeed Pakistan | B4: =COUNTIF(Cleaned_Data!H2:H156,A4) -> 67
A5: Glassdoor | B5: =COUNTIF(Cleaned_Data!H2:H156,A5) -> 37
A6: LinkedIn | B6: =COUNTIF(Cleaned_Data!H2:H156,A6) -> 19
A7: BeBee | B7: =COUNTIF(Cleaned_Data!H2:H156,A7) -> 17
A8: Rozee.pk | B8: =COUNTIF(Cleaned_Data!H2:H156,A8) -> 12
A9: Bayt.com | B9: =COUNTIF(Cleaned_Data!H2:H156,A9) -> 3

Sheet Summary_WorkMode_Experience
A1: Work Mode & Experience Level Distribution
A3: Work Mode | B3: Count
A4: Remote | B4: =COUNTIF(Cleaned_Data!M2:M156,A4) -> 11
A5: Onsite | B5: =COUNTIF(Cleaned_Data!M2:M156,A5) -> 7
A6: Hybrid | B6: =COUNTIF(Cleaned_Data!M2:M156,A6) -> 4
A7: Not disclosed | B7: =COUNTIF(Cleaned_Data!M2:M156,A7) -> 133
A9: Experience Level | B9: Count
A10: Entry/Fresh | B10: =COUNTIF(Cleaned_Data!O2:O156,A10) -> 13
A11: Mid | B11: =COUNTIF(Cleaned_Data!O2:O156,A11) -> 17
A12: Senior | B12: =COUNTIF(Cleaned_Data!O2:O156,A12) -> 26
A13: Not disclosed | B13: =COUNTIF(Cleaned_Data!O2:O156,A13) -> 99

Sheet Salary_Transparency
A1: Salary Disclosure Analysis
A3: Metric | B3: Value
A4: Total Listings | B4: =COUNTA(Cleaned_Data!A2:A156) -> 155
A5: Salary Disclosed (any form) | B5: =COUNTIF(Cleaned_Data!P2:P156,"Yes") -> 4
A6: Salary Not Disclosed | B6: =COUNTIF(Cleaned_Data!P2:P156,"No") -> 151
A7: % Disclosed | B7: =B5/B4 -> 0.025806452
A8: PKR listings with usable monthly figure | B8: =COUNTIF(Cleaned_Data!R2:R156,"PKR") -> 2
A9: USD listings with usable monthly figure | B9: =COUNTIF(Cleaned_Data!R2:R156,"USD") -> 1
A10: Average Disclosed Monthly Salary - PKR only | B10: =AVERAGEIF(Cleaned_Data!R2:R156,"PKR",Cleaned_Data!S2:S156) -> 76250
A11: Min Disclosed Monthly Salary - PKR only | B11: {=MIN(IF(Cleaned_Data!R2:R156="PKR",Cleaned_Data!S2:S156))} -> 32500
A12: Max Disclosed Monthly Salary - PKR only | B12: {=MAX(IF(Cleaned_Data!R2:R156="PKR",Cleaned_Data!S2:S156))} -> 120000
A14: Note: 'Not disclosed' values were NEVER estimated or filled with assumed numbers — this reflects real market opacity, consistent with PBS informal-wage-reporting patterns. USD hourly-rate listing excluded from monthly PKR comparison (different unit).

Sheet Skills_Demand
A1: In-Demand Skills / Keywords (from job titles & notes)
A3: Skill/Keyword | B3: Mentions
A4: Sql | B4: =SUMPRODUCT(--ISNUMBER(SEARCH(" sql ", " "&Cleaned_Data!U2:U156&" "))) -> 7
A5: Power Bi | B5: =SUMPRODUCT(--ISNUMBER(SEARCH(" power bi ", " "&Cleaned_Data!U2:U156&" "))) -> 13
A6: Python | B6: =SUMPRODUCT(--ISNUMBER(SEARCH(" python ", " "&Cleaned_Data!U2:U156&" "))) -> 5
A7: Business Intelligence | B7: =SUMPRODUCT(--ISNUMBER(SEARCH(" business intelligence ", " "&Cleaned_Data!U2:U156&" "))) -> 9
A8: Analytics | B8: =SUMPRODUCT(--ISNUMBER(SEARCH(" analytics ", " "&Cleaned_Data!U2:U156&" "))) -> 9
A9: Reporting | B9: =SUMPRODUCT(--ISNUMBER(SEARCH(" reporting ", " "&Cleaned_Data!U2:U156&" "))) -> 4
A10: Etl | B10: =SUMPRODUCT(--ISNUMBER(SEARCH(" etl ", " "&Cleaned_Data!U2:U156&" "))) -> 0
A11: Excel | B11: =SUMPRODUCT(--ISNUMBER(SEARCH(" excel ", " "&Cleaned_Data!U2:U156&" "))) -> 1
A12: Machine Learning | B12: =SUMPRODUCT(--ISNUMBER(SEARCH(" machine learning ", " "&Cleaned_Data!U2:U156&" "))) -> 1
A13: Data Warehouse | B13: =SUMPRODUCT(--ISNUMBER(SEARCH(" data warehouse ", " "&Cleaned_Data!U2:U156&" "))) -> 2
A14: Statistics | B14: =SUMPRODUCT(--ISNUMBER(SEARCH(" statistics ", " "&Cleaned_Data!U2:U156&" "))) -> 0
A15: Erp | B15: =SUMPRODUCT(--ISNUMBER(SEARCH(" erp ", " "&Cleaned_Data!U2:U156&" "))) -> 1
